<variables>
	<OPENWIKI_VERSION/>
	<OPENWIKI_REVISION/>
	<OPENWIKI_BUILD/>
	<OPENWIKI_XMLVERSION/>
	<OPENWIKI_NAMESPACE/>
	<DB_ACCESS/>
	<DB_ORACLE/>
	<DB_MYSQL/>
	<DB_POSTGRESQL/>
	<DB_SQLSERVER/>
	<UPLOADMETHOD_LEWISMOTEN/>
	<UPLOADMETHOD_ABCUPLOAD/>
	<UPLOADMETHOD_SAFILEUP/>
	<OPENWIKI_WELCOMEPAGE/>
	<OPENWIKI_DB_SYNTAX/>
	<OPENWIKI_ICONPATH/>
	<OPENWIKI_IMAGEPATH/>
	<OPENWIKI_ENCODING/>
	<OPENWIKI_TITLE/>
	<OPENWIKI_FRONTPAGE/>
	<OPENWIKI_SCRIPTNAME/>
	<OPENWIKI_MAXTEXT/>
	<OPENWIKI_MAXINCLUDELEVEL/>
	<OPENWIKI_RCNAME/>
	<OPENWIKI_RCDAYS/>
	<OPENWIKI_MAXTRAIL/>
	<OPENWIKI_TEMPLATES/>
	<OPENWIKI_TIMEZONE/>
	<OPENWIKI_MAXNROFAGGR/>
	<OPENWIKI_MAXWEBGETS/>
	<OPENWIKI_SCRIPTTIMEOUT/>
	<OPENWIKI_DAYSTOKEEP/>
	<OPENWIKI_STOPWORDS/>
	<OPENWIKI_UPLOADDIR/>
	<OPENWIKI_MAXUPLOADSIZE/>
	<OPENWIKI_UPLOADTIMEOUT/>
	<OPENWIKI_IMAGELIBRARY/>
	<OPENWIKI_UPLOADMETHOD/>
	<OPENWIKI_ACTIVESKIN/>
	<OPENWIKI_SYNONYMLINKPAGE/>
	<gSynonymArray/>
	<MSXML_VERSION/>
	<gDefaultBookmarks/>
	<cReadOnly/>
	<cNakedView/>
	<cUseSubpage/>
	<cFreeLinks/>
	<cWikiLinks/>
	<cAcronymLinks/>
	<cTemplateLinking/>
	<cRawHtml/>
	<cMathML/>
	<cHtmlTags/>
	<cCacheXSL/>
	<cCacheXML/>
	<cDirectEdit/>
	<cEmbeddedMode/>
	<cSimpleLinks/>
	<cNonEnglish/>
	<cNetworkFile/>
	<cBracketText/>
	<cBracketIndex/>
	<cHtmlLinks/>
	<cBracketWiki/>
	<cFreeUpper/>
	<cLinkImages/>
	<cUseHeadings/>
	<cUseLookup/>
	<cStripNTDomain/>
	<cMaskIPAddress/>
	<cOldSkool/>
	<cNewSkool/>
	<cNumTOC/>
	<cAllowCharRefs/>
	<cWikifyHeaders/>
	<cEmoticons/>
	<cUseLinkIcons/>
	<cPrettyLinks/>
	<cExternalOut/>
	<cAllowRSSExport/>
	<cAllowNewSyndications/>
	<cAllowAggregations/>
	<cNTAuthentication/>
	<cShowBrackets/>
	<cAllowAttachments/>
	<cAllowImageLibrary/>
	<cWriteHTML/>
	<cAutoComment/>
	<cUseParentRestrictions/>
	<cUseCategories/>
	<cAllowFlash/>
	<cAllowBadge/>
	<gLinkPattern/>
	<gSubpagePattern/>
	<gStopWords/>
	<gTimestampPattern/>
	<gUrlProtocols/>
	<gUrlPattern/>
	<gMailPattern/>
	<gInterSitePattern/>
	<gInterLinkPattern/>
	<gFreeLinkPattern/>
	<gImageExtensions/>
	<gImagePattern/>
	<gDocExtensions/>
	<gNotAcceptedExtensions/>
	<gISBNPattern/>
	<gHeaderPattern/>
	<gMacros/>
	<gUserSkin/>
	<gSystemSkin/>
	<gFS/>
	<gIndentLimit/>
	<gsz_lastPage/>
	<gsz_lastreferer/>
	<gPage/>
	<gRevision/>
	<gAction/>
	<gTxt/>
	<gServerRoot/>
	<gScriptName/>
	<gTransformer/>
	<gNamespace/>
	<gRaw/>
	<gBracketIndices/>
	<gTOC/>
	<gIncludeLevel/>
	<gCurrentWorkingPages/>
	<gIncludingAsTemplate/>
	<gNrOfRSSRetrievals/>
	<gAggregateURLs/>
	<gCookieHash/>
	<gTemp/>
	<gActionReturn/>
	<gMacroReturn/>
</variables>
